easypy/__init__.py
easypy/_multithreading_init.py
easypy/aliasing.py
easypy/bunch.py
easypy/caching.py
easypy/collections.py
easypy/colors.py
easypy/concurrency.py
easypy/contexts.py
easypy/decorations.py
easypy/deprecation.py
easypy/exceptions.py
easypy/fixtures.py
easypy/gevent.py
easypy/humanize.py
easypy/interaction.py
easypy/lockstep.py
easypy/logging.py
easypy/meta.py
easypy/misc.py
easypy/predicates.py
easypy/properties.py
easypy/random.py
easypy/resilience.py
easypy/signals.py
easypy/sync.py
easypy/tables.py
easypy/threadtree.py
easypy/timing.py
easypy/tokens.py
easypy/typed_struct.py
easypy/units.py
easypy/words.py
easypy/ziplog.py
tests/__init__.py
tests/conftest.py
tests/test_bunch.py
tests/test_caching.py
tests/test_collections.py
tests/test_concurrency.py
tests/test_contexts.py
tests/test_decorations.py
tests/test_deprecation.py
tests/test_humanize.py
tests/test_lockstep.py
tests/test_logging.py
tests/test_meta.py
tests/test_misc.py
tests/test_package.py
tests/test_randutils.py
tests/test_rwlock.py
tests/test_signals.py
tests/test_sync.py
tests/test_typed_struct.py
weka_easypy-0.3.0.dist-info/LICENSE
weka_easypy-0.3.0.dist-info/METADATA
weka_easypy-0.3.0.dist-info/WHEEL
weka_easypy-0.3.0.dist-info/top_level.txt
weka_easypy-0.3.0.dist-info/RECORD
