Metadata-Version: 2.1
Name: weka-easypy
Version: 0.3.0
Summary: easypy is a collection of python modules that makes developers happy
Home-page: https://github.com/weka-io/easypy
Author: Ofer Koren
Author-email: koreno@gmail.com
License: BSD
Platform: UNKNOWN
Classifier: Programming Language :: Python :: 3
Classifier: License :: OSI Approved :: BSD License
Classifier: Operating System :: OS Independent
